hrchy_cytocommunity/__init__.py
hrchy_cytocommunity/models/HRCHYCytoCommunity.py
hrchy_cytocommunity/models/__init__.py
hrchy_cytocommunity/models/auto_k.py
hrchy_cytocommunity/models/dataset.py
hrchy_cytocommunity/models/net.py
hrchy_cytocommunity/tools/__init__.py
hrchy_cytocommunity/tools/data_preprocessing.py
hrchy_cytocommunity/visualization/__init__.py
hrchy_cytocommunity/visualization/visualization.py
hrchy_cytocommunity-0.0.7.dist-info/licenses/LICENSE
hrchy_cytocommunity-0.0.7.dist-info/METADATA
hrchy_cytocommunity-0.0.7.dist-info/WHEEL
hrchy_cytocommunity-0.0.7.dist-info/top_level.txt
hrchy_cytocommunity-0.0.7.dist-info/RECORD
