Metadata-Version: 2.4
Name: hrchy_cytocommunity
Version: 0.0.7
Summary: A computational method for identifying hierarchical tissue structures in a cell phenotype-annotated cellular spatial map.
Author-email: Runzhi Xie <rzxie@stu.xidian.edu.cn>, Zekun Wang <22031212461@stu.xidian.edu.cn>, Lin Gao <lgao@mail.xidian.edu.cn>, Yuxuan Hu <huyuxuan@xidian.edu.cn>
Project-URL: Homepage, https://github.com/huBioinfo/HRCHY-CytoCommunity
Project-URL: Issues, https://github.com/huBioinfo/HRCHY-CytoCommunity/issues
Classifier: Programming Language :: Python :: 3
Classifier: License :: OSI Approved :: MIT License
Classifier: Operating System :: OS Independent
Requires-Python: >=3.10
License-File: LICENSE
Dynamic: license-file
